XToolsLib/FakeMail.py
XToolsLib/MailChecker.py
XToolsLib/Requests.py
XToolsLib/__init__.py
XToolsLib-0.1.dist-info/METADATA
XToolsLib-0.1.dist-info/WHEEL
XToolsLib-0.1.dist-info/top_level.txt
XToolsLib-0.1.dist-info/RECORD
